MANIFEST.in
requirements.txt
setup.cfg
setup.py
test_requirements.txt
eth_address_declarator/__init__.py
eth_address_declarator/declarator.py
eth_address_declarator/interface.py
eth_address_declarator/data/AddressDeclarator.bin
eth_address_declarator/data/AddressDeclarator.json
eth_address_declarator/data/AddressDeclarator.metadata.json
eth_address_declarator/runnable/add.py
eth_address_declarator/runnable/publish.py
eth_address_declarator/runnable/view.py
eth_address_declarator/unittest/__init__.py
eth_address_declarator/unittest/addressdeclarator.py
eth_address_index.egg-info/PKG-INFO
eth_address_index.egg-info/SOURCES.txt
eth_address_index.egg-info/dependency_links.txt
eth_address_index.egg-info/entry_points.txt
eth_address_index.egg-info/requires.txt
eth_address_index.egg-info/top_level.txt
tests/test_addressdeclarator.py
tests/test_addressdeclarator_kv.py