Metadata-Version: 2.1
Name: eth-address-index
Version: 0.7.3
Summary: Signed metadata declarations for ethereum addresses
Home-page: https://holbrook.no/src/eth-address-index/log.html
Author: Louis Holbrook
Author-email: dev@holbrook.no
License: AGPLv3+
Keywords: ethereum
Classifier: Programming Language :: Python :: 3
Classifier: Operating System :: OS Independent
Classifier: Development Status :: 4 - Beta
Classifier: Environment :: Console
Classifier: Intended Audience :: Developers
Classifier: License :: OSI Approved :: GNU Affero General Public License v3 or later (AGPLv3+)
Classifier: Topic :: Internet
Classifier: Topic :: Software Development :: Libraries
Requires-Python: >=3.7
Provides-Extra: dev
